fast_dijkstra.cpython-312-x86_64-linux-gnu.so
fast_dijkstra.libs/libgomp-e985bcbb.so.1.0.0
fast_dijkstra-2.1.2.dist-info/METADATA
fast_dijkstra-2.1.2.dist-info/WHEEL
fast_dijkstra-2.1.2.dist-info/top_level.txt
fast_dijkstra-2.1.2.dist-info/RECORD
fast_dijkstra-2.1.2.dist-info/sboms/auditwheel.cdx.json
