Metadata-Version: 2.4
Name: fast_dijkstra
Version: 2.1.2
Summary: Fast Dijkstra
Author-email: Simon Boivin <sboivin@systra.com>
Project-URL: Homepage, https://github.com/sboivinsystra/fast_dijkstra
